hstrader/__init__.py
hstrader/config/__init__.py
hstrader/config/config.py
hstrader/helpers/__init__.py
hstrader/helpers/http.py
hstrader/helpers/user_agent.py
hstrader/helpers/ws.py
hstrader/hstrader/__init__.py
hstrader/hstrader/hstrader.py
hstrader/models/__init__.py
hstrader/models/account.py
hstrader/models/auth.py
hstrader/models/base.py
hstrader/models/base_response.py
hstrader/models/deal.py
hstrader/models/enums.py
hstrader/models/events.py
hstrader/models/market.py
hstrader/models/order.py
hstrader/models/position.py
hstrader/models/symbol.py
hstrader/models/utils.py
hstrader/models/ws.py
hstrader/services/__init__.py
hstrader/services/account.py
hstrader/services/auth.py
hstrader/services/deal.py
hstrader/services/market.py
hstrader/services/order.py
hstrader/services/position.py
hstrader/services/symbol.py
hstrader/services/urls.py
hstrader/services/utils.py
hstrader/services/ws.py
hstrader-1.1.0.dist-info/WHEEL
hstrader-1.1.0.dist-info/METADATA
hstrader-1.1.0.dist-info/RECORD
