Metadata-Version: 2.1
Name: hstrader
Version: 1.1.0
Summary: HsTrader SDK for Python
Author: Hybrid Solutions
Author-email: dev@hybridsolutions.com
Requires-Python: >=3.7,<4.0
Classifier: Programming Language :: Python :: 3
Classifier: Programming Language :: Python :: 3.10
Classifier: Programming Language :: Python :: 3.7
Classifier: Programming Language :: Python :: 3.8
Classifier: Programming Language :: Python :: 3.9
Requires-Dist: pydantic
Requires-Dist: requests
Requires-Dist: websockets
